swarmauri_mre_crypto_ecdh_es_kw/EcdhEsA128KwMreCrypto.py
swarmauri_mre_crypto_ecdh_es_kw/__init__.py
swarmauri_mre_crypto_ecdh_es_kw-0.2.0.dev5.dist-info/LICENSE
swarmauri_mre_crypto_ecdh_es_kw-0.2.0.dev5.dist-info/METADATA
swarmauri_mre_crypto_ecdh_es_kw-0.2.0.dev5.dist-info/WHEEL
swarmauri_mre_crypto_ecdh_es_kw-0.2.0.dev5.dist-info/entry_points.txt
swarmauri_mre_crypto_ecdh_es_kw-0.2.0.dev5.dist-info/RECORD
