Metadata-Version: 2.3
Name: swarmauri_mre_crypto_ecdh_es_kw
Version: 0.2.0.dev5
Summary: ECDH-ES+A128KW based multi-recipient encryption provider for Swarmauri
License: Apache-2.0
Author: Swarmauri
Author-email: opensource@swarmauri.com
Requires-Python: >=3.10,<3.13
Classifier: License :: OSI Approved :: Apache Software License
Classifier: Natural Language :: English
Classifier: Programming Language :: Python :: 3.10
Classifier: Programming Language :: Python :: 3.11
Classifier: Programming Language :: Python :: 3.12
Classifier: Programming Language :: Python :: 3.13
Classifier: Development Status :: 3 - Alpha
Classifier: Topic :: Security :: Cryptography
Classifier: Intended Audience :: Developers
Provides-Extra: cbor
Requires-Dist: cbor2 ; extra == "cbor"
Requires-Dist: cryptography (>=41)
Requires-Dist: swarmauri_base
Requires-Dist: swarmauri_core
